sarcastic/__init__.py
sarcastic/__main__.py
sarcastic-0.1.1.dist-info/LICENSE
sarcastic-0.1.1.dist-info/METADATA
sarcastic-0.1.1.dist-info/WHEEL
sarcastic-0.1.1.dist-info/entry_points.txt
sarcastic-0.1.1.dist-info/top_level.txt
sarcastic-0.1.1.dist-info/RECORD
