Metadata-Version: 2.1
Name: sarcastic
Version: 0.1.1
Summary: sarcastic mAkEs YoUr tExT SaRcAsTiC.
Home-page: https://github.com/calebe94/sarcastic
Author: Edimar Calebe Castanho
Author-email: contato@calebe.dev.br
License: GPL3+
Project-URL: Bug Tracker, https://github.com/calebe94/sarcastic/issues
Classifier: Programming Language :: Python :: 3
Classifier: License :: OSI Approved :: GNU General Public License v3 or later (GPLv3+)
Classifier: Operating System :: POSIX
Requires-Python: >=3.6
License-File: LICENSE
